[
  {
    "name": "kafka_partition",
    "type": "INTEGER",
    "mode": "NULLABLE",
    "description": ""
  },
  {
    "name": "kafka_offset",
    "type": "INTEGER",
    "mode": "NULLABLE",
    "description": ""
  },
  {
    "name": "symbol",
    "type": "STRING",
    "mode": "NULLABLE",
    "description": ""
  },
  {
    "name": "trade_date",
    "type": "DATE",
    "mode": "NULLABLE",
    "description": ""
  },
  {
    "name": "event_date",
    "type": "DATE",
    "mode": "NULLABLE",
    "description": ""
  },
  {
    "name": "exchange_timestamp",
    "type": "TIMESTAMP",
    "mode": "NULLABLE",
    "description": ""
  },
  {
    "name": "hw_nic_rx_timestamp",
    "type": "TIMESTAMP",
    "mode": "NULLABLE",
    "description": ""
  },
  {
    "name": "mako_ingress_timestamp",
    "type": "TIMESTAMP",
    "mode": "NULLABLE",
    "description": ""
  },
  {
    "name": "software_timestamp",
    "type": "TIMESTAMP",
    "mode": "NULLABLE",
    "description": ""
  },
  {
    "name": "exchange_timestamp_ns",
    "type": "INTEGER",
    "mode": "NULLABLE",
    "description": ""
  },
  {
    "name": "hw_nic_rx_timestamp_ns",
    "type": "INTEGER",
    "mode": "NULLABLE",
    "description": ""
  },
  {
    "name": "mako_ingress_timestamp_ns",
    "type": "INTEGER",
    "mode": "NULLABLE",
    "description": ""
  },
  {
    "name": "software_timestamp_ns",
    "type": "INTEGER",
    "mode": "NULLABLE",
    "description": ""
  },
  {
    "name": "instrument_hash",
    "type": "STRING",
    "mode": "NULLABLE",
    "description": ""
  },
  {
    "name": "event_type",
    "type": "INTEGER",
    "mode": "NULLABLE",
    "description": ""
  },
  {
    "name": "sequence_number",
    "type": "INTEGER",
    "mode": "NULLABLE",
    "description": ""
  },
  {
    "name": "side",
    "type": "INTEGER",
    "mode": "NULLABLE",
    "description": ""
  },
  {
    "name": "price",
    "type": "FLOAT",
    "mode": "NULLABLE",
    "description": ""
  },
  {
    "name": "quantity",
    "type": "INTEGER",
    "mode": "NULLABLE",
    "description": ""
  },
  {
    "name": "order_id",
    "type": "INTEGER",
    "mode": "NULLABLE",
    "description": ""
  },
  {
    "name": "order_position",
    "type": "INTEGER",
    "mode": "NULLABLE",
    "description": ""
  },
  {
    "name": "market_state",
    "type": "INTEGER",
    "mode": "NULLABLE",
    "description": ""
  },
  {
    "name": "keyframe",
    "type": "BOOLEAN",
    "mode": "NULLABLE",
    "description": ""
  },
  {
    "name": "instrument_type",
    "type": "STRING",
    "mode": "NULLABLE",
    "description": ""
  },
  {
    "name": "data_order_identifier",
    "type": "INTEGER",
    "mode": "NULLABLE",
    "description": ""
  },
  {
    "name": "data_timestamp",
    "type": "TIMESTAMP",
    "mode": "NULLABLE",
    "description": ""
  },
  {
    "name": "data_timestamp_ns",
    "type": "INTEGER",
    "mode": "NULLABLE",
    "description": ""
  },
  {
    "name": "is_snap",
    "type": "BOOLEAN",
    "mode": "NULLABLE",
    "description": ""
  },
  {
    "name": "strike",
    "type": "FLOAT",
    "mode": "NULLABLE",
    "description": ""
  },
  {
    "name": "option_type",
    "type": "INTEGER",
    "mode": "NULLABLE",
    "description": ""
  },
  {
    "name": "option_type_name",
    "type": "STRING",
    "mode": "NULLABLE",
    "description": ""
  },
  {
    "name": "expiry_timestamp",
    "type": "TIMESTAMP",
    "mode": "NULLABLE",
    "description": ""
  },
  {
    "name": "mako_symbol",
    "type": "STRING",
    "mode": "NULLABLE",
    "description": ""
  },
  {
    "name": "currency",
    "type": "INTEGER",
    "mode": "NULLABLE",
    "description": ""
  },
  {
    "name": "term",
    "type": "STRING",
    "mode": "NULLABLE",
    "description": ""
  },
  {
    "name": "inst_type_name",
    "type": "STRING",
    "mode": "NULLABLE",
    "description": ""
  },
  {
    "name": "cancel_quantity",
    "type": "STRING",
    "mode": "NULLABLE",
    "description": ""
  },
  {
    "name": "hidden_quantity",
    "type": "STRING",
    "mode": "NULLABLE",
    "description": ""
  },
  {
    "name": "fill_quantity",
    "type": "STRING",
    "mode": "NULLABLE",
    "description": ""
  },
  {
    "name": "mako_sequence_number",
    "type": "INTEGER",
    "mode": "NULLABLE",
    "description": ""
  },
  {
    "name": "streamsource_stream_id",
    "type": "INTEGER",
    "mode": "NULLABLE",
    "description": ""
  },
  {
    "name": "streamsource_event_id",
    "type": "INTEGER",
    "mode": "NULLABLE",
    "description": ""
  },
  {
    "name": "streamsource_message_id",
    "type": "INTEGER",
    "mode": "NULLABLE",
    "description": ""
  },
  {
    "name": "datasource_pid",
    "type": "INTEGER",
    "mode": "NULLABLE",
    "description": ""
  },
  {
    "name": "datasource_hostname",
    "type": "STRING",
    "mode": "NULLABLE",
    "description": ""
  }
]
